heatgeo/__init__.py
heatgeo/_modidx.py
heatgeo/cheb.py
heatgeo/embedding.py
heatgeo/graph.py
heatgeo/heat_filter.py
heatgeo/mds.py
heatgeo/other_emb.py
heatgeo/utils.py
heatgeo-0.0.1.dist-info/LICENSE
heatgeo-0.0.1.dist-info/METADATA
heatgeo-0.0.1.dist-info/WHEEL
heatgeo-0.0.1.dist-info/entry_points.txt
heatgeo-0.0.1.dist-info/top_level.txt
heatgeo-0.0.1.dist-info/RECORD
