Metadata-Version: 2.1
Name: heatgeo
Version: 0.0.1
Summary: Heat geodesic embeddings
Home-page: https://github.com/KrishnaswamyLab/heatgeo
Author: guillaumehu
Author-email: guillaumehuguet2@gmail.com
License: Apache Software License 2.0
Keywords: nbdev jupyter notebook python
Classifier: Development Status :: 4 - Beta
Classifier: Intended Audience :: Developers
Classifier: Natural Language :: English
Classifier: Programming Language :: Python :: 3.7
Classifier: Programming Language :: Python :: 3.8
Classifier: Programming Language :: Python :: 3.9
Classifier: Programming Language :: Python :: 3.10
Classifier: License :: OSI Approved :: Apache Software License
Requires-Python: >=3.7
License-File: LICENSE
Requires-Dist: graphtools (==1.5.3)
Requires-Dist: networkx (==2.8.6)
Requires-Dist: numpy (==1.23.5)
Requires-Dist: PyGSP (==0.5.1)
Requires-Dist: s-gd2 (==1.8.1)
Requires-Dist: scikit-learn (==1.2.2)
Requires-Dist: setuptools
Requires-Dist: scipy
Requires-Dist: kneed
Provides-Extra: dev
Requires-Dist: hydra-core (==1.3.2) ; extra == 'dev'
Requires-Dist: omegaconf (==2.3.0) ; extra == 'dev'
Requires-Dist: python-dotenv (==1.0.0) ; extra == 'dev'
Requires-Dist: phate (==1.0.10) ; extra == 'dev'
Requires-Dist: scanpy (==1.9.3) ; extra == 'dev'
Requires-Dist: scprep (==1.2.1) ; extra == 'dev'
Requires-Dist: POT ; extra == 'dev'
Requires-Dist: umap ; extra == 'dev'
